nonebot_plugin_pokemonle-0.0.7.dist-info/METADATA
nonebot_plugin_pokemonle-0.0.7.dist-info/WHEEL
nonebot_plugin_pokemonle-0.0.7.dist-info/entry_points.txt
nonebot_plugin_pokemonle-0.0.7.dist-info/licenses/LICENSE
nonebot_plugin_pokemonle/__init__.py
nonebot_plugin_pokemonle/config.py
nonebot_plugin_pokemonle/game.py
nonebot_plugin_pokemonle/render.py
nonebot_plugin_pokemonle/resources/data/ability/001-恶臭.json
nonebot_plugin_pokemonle/resources/data/ability/002-降雨.json
nonebot_plugin_pokemonle/resources/data/ability/003-加速.json
nonebot_plugin_pokemonle/resources/data/ability/004-战斗盔甲.json
nonebot_plugin_pokemonle/resources/data/ability/005-结实.json
nonebot_plugin_pokemonle/resources/data/ability/006-湿气.json
nonebot_plugin_pokemonle/resources/data/ability/007-柔软.json
nonebot_plugin_pokemonle/resources/data/ability/008-沙隐.json
nonebot_plugin_pokemonle/resources/data/ability/009-静电.json
nonebot_plugin_pokemonle/resources/data/ability/010-蓄电.json
nonebot_plugin_pokemonle/resources/data/ability/011-储水.json
nonebot_plugin_pokemonle/resources/data/ability/012-迟钝.json
nonebot_plugin_pokemonle/resources/data/ability/013-无关天气.json
nonebot_plugin_pokemonle/resources/data/ability/014-复眼.json
nonebot_plugin_pokemonle/resources/data/ability/015-不眠.json
nonebot_plugin_pokemonle/resources/data/ability/016-变色.json
nonebot_plugin_pokemonle/resources/data/ability/017-免疫.json
nonebot_plugin_pokemonle/resources/data/ability/018-引火.json
nonebot_plugin_pokemonle/resources/data/ability/019-鳞粉.json
nonebot_plugin_pokemonle/resources/data/ability/020-我行我素.json
nonebot_plugin_pokemonle/resources/data/ability/021-吸盘.json
nonebot_plugin_pokemonle/resources/data/ability/022-威吓.json
nonebot_plugin_pokemonle/resources/data/ability/023-踩影.json
nonebot_plugin_pokemonle/resources/data/ability/024-粗糙皮肤.json
nonebot_plugin_pokemonle/resources/data/ability/025-神奇守护.json
nonebot_plugin_pokemonle/resources/data/ability/026-飘浮.json
nonebot_plugin_pokemonle/resources/data/ability/027-孢子.json
nonebot_plugin_pokemonle/resources/data/ability/028-同步.json
nonebot_plugin_pokemonle/resources/data/ability/029-恒净之躯.json
nonebot_plugin_pokemonle/resources/data/ability/030-自然回复.json
nonebot_plugin_pokemonle-0.0.7.dist-info/RECORD
