Metadata-Version: 2.4
Name: nonebot-plugin-pokemonle
Version: 0.0.7
Summary: 猜宝可梦
Author-Email: Proito666 <Proito666@github.com>
License-Expression: MIT
Project-URL: repository, https://github.com/Proito666/nonebot-plugin-pokemonle
Requires-Python: <4.0,>=3.9
Requires-Dist: nonebot2<3.0.0,>=2.3.0
Requires-Dist: nonebot-plugin-htmlrender<1.0.0,>=0.2.0
Requires-Dist: nonebot-plugin-alconna<1.0.0,>=0.25.0
Requires-Dist: pypinyin>=0.54.0
Requires-Dist: nonebot-plugin-uninfo>=0.7.3
Requires-Dist: jinja2>=3.1.6
